{
    "Authors": [
        "Artur Gomes",
        "Vitor Figueira"
    ],
    "Description": "Gold Panic Solver is a program that uses the A star (A*) algorithm to solve some levels of the game Gold Panic.",
    "Media": [
        "project_data/College/Year 3/Gold Panic Solver/ia1.jpg",
        "project_data/College/Year 3/Gold Panic Solver/ia2.jpg",
        "project_data/College/Year 3/Gold Panic Solver/ia3.jpg",
        "project_data/College/Year 3/Gold Panic Solver/ia4.jpg",
        "project_data/College/Year 3/Gold Panic Solver/ia5.jpg"
    ],
    "ProjectName": "Gold Panic Solver",
    "State": "",
    "Subject": "Intelig\u00eancia Artificual",
    "Tags": [
        "Java"
    ],
    "URL": {}
}