{
    "Authors": [
        "Artur Gomes",
        "Vitor Figueira",
        "Mariana Lopes"
    ],
    "Description": "This project main goal was to create a game using augmented reality. Therefore we created a game in which we used the augmented reality symbols to create a control board, which would control 2 cannons. The main objective of this game is to destroy the other cannon.",
    "Media": [
        "project_data/university/Year 5/ARCannons/Captura de tela 2013-11-07 22.51.39.jpg",
        "project_data/university/Year 5/ARCannons/Captura de tela 2013-11-09 12.52.17.jpg",
        "project_data/university/Year 5/ARCannons/marcs.jpg",
        "project_data/university/Year 5/ARCannons/models.jpg"
    ],
    "ProjectName": "ARCannons",
    "State": "",
    "Subject": "Augmented and Virtual Reality",
    "Tags": [
        "ARToolKit",
        "C++"
    ],
    "URL": {}
}